{
    "host": "taxi-dev01.taxi21.ru",
    "port": 22,
    "username": "user",
    "password": "123456",
    "protocol": "sftp",
    "agent": null,
    "privateKeyPath": null,
    "passphrase": null,
    "passive": false,
    "interactiveAuth": false,
    "remotePath": "/home/user/vott_rus_bot/",
    "uploadOnSave": true,
    "syncMode": "update",
    "watcher": {
        "files": false,
        "autoUpload": false,
        "autoDelete": false
    },
    "ignore": [
        "**/.vscode/**",
        "**/.git/**",
        "**/.DS_Store",
        "node_modules"
    ]
}